youtube_creator_mcp/__init__.py
youtube_creator_mcp/server.py
youtube_creator_mcp/youtube_api.py
youtube_creator_mcp-1.0.0.dist-info/METADATA
youtube_creator_mcp-1.0.0.dist-info/WHEEL
youtube_creator_mcp-1.0.0.dist-info/entry_points.txt
youtube_creator_mcp-1.0.0.dist-info/RECORD
