Metadata-Version: 2.4
Name: youtube-creator-mcp
Version: 1.0.0
Summary: YouTube automation MCP: upload videos, Shorts, manage playlists, analytics
Project-URL: Homepage, https://github.com/MarceauSolutions/dev-sandbox/tree/main/projects/youtube-creator
Project-URL: Repository, https://github.com/MarceauSolutions/dev-sandbox
Author-email: "William Marceau Jr." <william@marceausolutions.com>
License-Expression: MIT
Keywords: automation,creator,mcp,shorts,upload,video,youtube
Classifier: Development Status :: 4 - Beta
Classifier: Intended Audience :: Developers
Classifier: License :: OSI Approved :: MIT License
Classifier: Programming Language :: Python :: 3
Classifier: Programming Language :: Python :: 3.10
Classifier: Programming Language :: Python :: 3.11
Classifier: Programming Language :: Python :: 3.12
Requires-Python: >=3.10
Requires-Dist: google-api-python-client>=2.0.0
Requires-Dist: google-auth-httplib2>=0.1.0
Requires-Dist: google-auth-oauthlib>=1.0.0
Requires-Dist: mcp>=1.0.0
